notify_events/__init__.py
notify_events/message.py
notify_events-1.1.3.dist-info/LICENSE
notify_events-1.1.3.dist-info/METADATA
notify_events-1.1.3.dist-info/WHEEL
notify_events-1.1.3.dist-info/top_level.txt
notify_events-1.1.3.dist-info/RECORD
