Metadata-Version: 2.1
Name: notify-events
Version: 1.1.3
Summary: Extension to integrate your project with Notify.Events service.
Home-page: https://github.com/notify-events/python
Author: Notify.Events
Author-email: support@notify.events
License: MIT
Keywords: notification,alert,teams,viber,telegram,signal,slack,sms,voice,call
Platform: UNKNOWN
Classifier: License :: OSI Approved :: MIT License
Classifier: Programming Language :: Python :: 3
Classifier: Programming Language :: Python :: 3.7
Requires-Dist: requests
